{"baseIcon":"album/e/0/3/00000000000ee30e/4/square-200.jpg","releaseDate":"2011-09-12","artistUrl":"/artist/Ed_Sheeran/","duration":3935,"isClean":false,"shortUrl":"http://rd.io/x/QVl3eCJRsU8/","canStream":true,"embedUrl":"https://rd.io/e/QVl3eCJRsU8/","type":"a","price":"9.99","key":"a975630","icon":"http://rdio-b.cdn3.rdio.com/album/e/0/3/00000000000ee30e/4/square-200.jpg","canSample":true,"name":"+","isExplicit":false,"artist":"Ed Sheeran","url":"/artist/Ed_Sheeran/album/%2B/","artistKey":"r543097","length":16,"trackKeys":["t11348714","t11348798","t11348861","t11348934","t11348994","t11349064","t11349145","t11349213","t11349282","t11349339","t11349404","t11349462","t11349552","t11349589","t11349619","t11349654"],"canTether":true,"displayDate":"Sep 12, 2011"}