{"radioKey":"sr20733304|3","baseIcon":"album/d/a/0/00000000001d50ad/4/square-200.jpg","canDownloadAlbumOnly":true,"radio":{"type":"sr","key":"sr20733304|3"},"artistUrl":"/artist/P!nk/","duration":162,"album":"The Truth About Love","isClean":false,"albumUrl":"/artist/P!nk/album/The_Truth_About_Love/","shortUrl":"http://rd.io/x/QVl3eDdebhw8/","albumArtist":"P!nk","canStream":true,"embedUrl":"https://rd.io/e/QVl3eDdebhw8/","type":"t","price":"1.29","trackNum":10,"albumArtistKey":"r91332","key":"t20733304","icon":"http://rdio-d.cdn3.rdio.com/album/d/a/0/00000000001d50ad/4/square-200.jpg","canSample":true,"name":"Walk of Shame","isExplicit":true,"artistKey":"r91332","url":"/artist/P!nk/album/The_Truth_About_Love/track/Walk_of_Shame/","icon400":"http://rdio-b.cdn3.rdio.com/album/d/a/0/00000000001d50ad/4/square-400.jpg","artist":"P!nk","canDownload":true,"length":1,"canTether":true,"albumKey":"a1921197"}